_black_version.py
black/__init__.py
black/__main__.py
black/brackets.py
black/cache.py
black/comments.py
black/concurrency.py
black/const.py
black/debug.py
black/files.py
black/handle_ipynb_magics.py
black/linegen.py
black/lines.py
black/mode.py
black/nodes.py
black/numerics.py
black/output.py
black/parsing.py
black/py.typed
black/report.py
black/rusty.py
black/strings.py
black/trans.py
black_primer/__init__.py
black_primer/cli.py
black_primer/lib.py
black_primer/primer.json
blackd/__init__.py
blackd/__main__.py
blackd/middlewares.py
blib2to3/Grammar.txt
blib2to3/PatternGrammar.txt
blib2to3/__init__.py
blib2to3/pygram.py
blib2to3/pytree.py
blib2to3/pgen2/__init__.py
blib2to3/pgen2/conv.py
blib2to3/pgen2/driver.py
blib2to3/pgen2/grammar.py
blib2to3/pgen2/literals.py
blib2to3/pgen2/parse.py
blib2to3/pgen2/pgen.py
blib2to3/pgen2/token.py
blib2to3/pgen2/tokenize.py
noir-22.1.0.0.dist-info/AUTHORS.md
noir-22.1.0.0.dist-info/LICENSE
noir-22.1.0.0.dist-info/METADATA
noir-22.1.0.0.dist-info/WHEEL
noir-22.1.0.0.dist-info/entry_points.txt
noir-22.1.0.0.dist-info/top_level.txt
noir-22.1.0.0.dist-info/RECORD
